{"name":"HTTP","postlist":[{"title":"Http Configure the source tree","slug":"http-modules","date":"2017-04-29T01:24:28.000Z","updated":"2017-11-19T13:15:37.000Z","comments":true,"path":"api/articles/http-modules.json","excerpt":"","keywords":null,"content":null,"raw":null,"categories":[],"tags":[{"name":"HTTP","path":"api/tags/HTTP.json"},{"name":"modules","path":"api/tags/modules.json"}]}]}date":"2017-04-20T08:08:51.000Z","updated":"2017-12-09T13:55:26.000Z","comments":true,"path":"api/articles/lvs-nat.json","excerpt":"","keywords":null,"content":null,"raw":null,"categories":[],"tags":[{"name":"Http","path":"api/tags/Http.json"},{"name":"Https","path":"api/tags/Https.json"}]}]}