{"name":"nginx","postlist":[{"title":"nginx配置及调优","slug":"Nginx配置及优化","date":"2017-05-14T07:42:51.000Z","updated":"2017-11-19T13:15:37.000Z","comments":true,"path":"api/articles/Nginx配置及优化.json","excerpt":"","keywords":null,"content":null,"raw":null,"categories":[],"tags":[{"name":"web","path":"api/tags/web.json"},{"name":"nginx","path":"api/tags/nginx.json"}]},{"title":"nginx负载均衡","slug":"nginx负载均衡","date":"2017-05-15T08:20:11.000Z","updated":"2017-11-19T13:15:37.000Z","comments":true,"path":"api/articles/nginx负载均衡.json","excerpt":"","keywords":null,"content":null,"raw":null,"categories":[],"tags":[{"name":"nginx","path":"api/tags/nginx.json"},{"name":"负载均衡","path":"api/tags/负载均衡.json"}]}]}